parameter_expansion/__init__.py
parameter_expansion/pe.py
parameter_expansion/tests/test_pe.py
parameter_expansion-0.2.0.dist-info/LICENSE
parameter_expansion-0.2.0.dist-info/WHEEL
parameter_expansion-0.2.0.dist-info/METADATA
parameter_expansion-0.2.0.dist-info/RECORD
