Metadata-Version: 2.1
Name: parameter-expansion
Version: 0.2.0
Summary: POSIX parameter expansion in Python
Author: Michael A. Smith
Author-email: michael@smith-li.com
Requires-Python: >=3.6,<4.0
Classifier: Programming Language :: Python :: 3
Classifier: Programming Language :: Python :: 3.6
Classifier: Programming Language :: Python :: 3.7
Classifier: Programming Language :: Python :: 3.8
Classifier: Programming Language :: Python :: 3.9
